[
     {
          "listOfSubColourPalettes": [{
               "listOfSubColourPalettes": [],
               "paletteName": "Blue",
               "listOfColours": [{
                    "name": "blue",
                    "hex": "#0000FF"
               }]
          }],
          "paletteName": "Sunset",
          "listOfColours": [
               {
                    "name": "Red",
                    "hex": "#f73f39"
               },
               {
                    "name": "Purple",
                    "hex": "#d47dba"
               },
               {
                    "name": "Yellow",
                    "hex": "#f7cb39"
               },
               {
                    "name": "Orange",
                    "hex": "#f58f22"
               }
          ]
     },
     {
          "listOfSubColourPalettes": [],
          "paletteName": "Ocean",
          "listOfColours": [
               {
                    "name": "Sky Blue",
                    "hex": "#03bafc"
               },
               {
                    "name": "Light Blue",
                    "hex": "#a6f0ff"
               },
               {
                    "name": "Deep Aqua",
                    "hex": "#009bb3"
               },
               {
                    "name": "Cool Blue",
                    "hex": "#4bcdeb"
               }
          ]
     },
     {
          "listOfSubColourPalettes": [],
          "paletteName": "Skin Tones",
          "listOfColours": [
               {
                    "name": "Light",
                    "hex": "#fdf5e2"
               },
               {
                    "name": "Yellower Light",
                    "hex": "#fdf1cb"
               },
               {
                    "name": "Richer Light",
                    "hex": "#fddcb4"
               },
               {
                    "name": "Tan",
                    "hex": "#C68863"
               },
               {
                    "name": "Light Dark",
                    "hex": "#B06C49"
               },
               {
                    "name": "Dark",
                    "hex": "#743D2B"
               }
          ]
     },
     {
          "listOfSubColourPalettes": [],
          "paletteName": "Empty Palette",
          "listOfColours": []
     }
]